Workbook

Sheet 使い方
B1: OEMリサーチ管理シート
B3: ■ 作業の流れ
B4: ① キーワード … 検索するキーワードを決める（案を入れてあります）
B5: ② セラーリスト … 検索結果から中国から仕入れていそうなセラーを記録する
B6: ③ 商品候補 … 良さそうなセラーの商品を記録する（ASIN・価格・BSR・レビュー数など）
B7: ④ 上位10件データ → ライバル調査 … 候補商品のキーワードで検索し、上位10件を入力すると自動で判定される
B8: ⑤ 利益計算 … 仕入れ値を入れると、1個あたりの利益・目標達成に必要な販売数・予算内の仕入れ数が出る
B10: ■ セルの色の意味
B11: 黄色の背景・青い文字 … あなたが入力するセル
B12: 白の背景・黒い文字 … 自動計算（触らない）
B13: 灰色の背景 … 記入例の行（参考にしたら消すか上書きしてOK）
B15: ■ 判定基準・手数料などの数値は「設定」シートで変更できます
... B23: ・商品画像が似たテンプレート、日本語説明文がやや不自然

Sheet 設定
A1: 項目 | B1: 値 | C1: 説明・出典
A2: ■ 目標・予算
A3: 月の目標利益（円） | B3: 50000 | C3: あなたの目標（ユーザー指定）
A4: 初回の仕入れ予算（円） | B4: 50000 | C4: あなたの予算（ユーザー指定）
A5: ■ コストの前提
A6: 為替（1元＝円） | B6: 21 | C6: 仮の値。仕入れ時に最新レートへ更新してください
A7: 仕入れ代行手数料率 | B7: 0.05 | C7: 代行業者により3〜10%程度。契約先の料金に合わせて変更
A8: 関税率（衣類） | B8: 0.1 | C8: 衣類はおおむね4〜13%（素材・種類で異なる）。仮で10%。正確な税率は税関の輸入統計品目表で確認
A9: 輸入消費税率 | B9: 0.1 | C9: 輸入時の消費税。簡易化のため（仕入れ値＋送料＋関税）に掛けて計算
A10: Amazon販売手数料率 | B10: 0.08 | C10: 服&ファッション小物は価格帯で料率が変わる（3,000円以下は低い料率）。セラーセントラルの手数料ページで要確認
A11: FBA配送代行手数料（円/個） | B11: 320 | C11: SellerSprite出力(10/12)のネックウォーマー実績: 小型222〜288円・標準252〜430円。商品ごとに要確認
A12: その他経費（円/個） | B12: 50 | C12: タグ・袋・FBAラベル・倉庫保管料などの概算
A13: ■ ライバル調査の合格ライン
A14: 上位10件の平均月販 ≥（個） | B14: 100 | C14: 需要があるかの目安。低いと売れない
A15: レビュー1,000件以上の強者の数 ≤ | B15: 3 | C15: 多いと勝てない
A16: レビュー100件未満の出品の数 ≥ | B16: 3 | C16: 新しい出品でも上位にいる＝新規参入の余地あり
A17: 上位10件の平均価格 下限（円） | B17: 1800 | C17: 安すぎると利益が残らない
A18: 上位10件の平均価格 上限（円） | B18: 3500 | C18: あなたの価格帯（3,000円弱）の周辺
A19: 合格項目数（5項目中）◎ | B19: 5 | C19: この数以上なら「◎ 有力」
A20: 合格項目数（5項目中）○ | B20: 4 | C20: この数以上なら「○ 候補」、未満は「△」「×」
A21: ■ 利益の合格ライン
A22: 最低利益率 | B22: 0.25 | C22: 販売価格に対する利益の割合
A23: 最低1個あたり利益（円） | B23: 500

Sheet キーワード
A1: No | B1: キーワード | C1: ジャンル | D1: 季節 | E1: サイズ展開 | F1: 検索した日 | G1: 拾えたセラー数 | H1: 状態 | I1: メモ
A2: 1 | B2: ネックウォーマー 裏起毛 | C2: 防寒小物 | D2: 秋冬 | E2: フリー | F2: 2026/10/12 | G2: 33 | H2: 調査中 | I2: 不満は「サイズ」「息で濡れる/息苦しい」「検品不足」に集中。立体口元＋調整コード＋長めの首丈で差別化案
A3: 2 | B3: レッグウォーマー | C3: 防寒小物 | D3: 秋冬 | E3: フリー | H3: 未着手
A4: 3 | B4: スマホ対応 手袋 レディース | C4: 防寒小物 | D4: 秋冬 | E4: フリー | H4: 未着手
A5: 4 | B5: ニット帽 レディース | C5: 帽子 | D5: 秋冬 | E5: フリー | H5: 未着手
A6: 5 | B6: 腹巻き 綿 | C6: インナー | D6: 秋冬 | E6: フリー | H6: 未着手
A7: 6 | B7: ルームソックス もこもこ | C7: 靴下 | D7: 秋冬 | E7: フリー | H7: 未着手
A8: 7 | B8: ブランケット 着る | C8: ルームウェア | D8: 秋冬 | E8: フリー | H8: 未着手
A9: 8 | B9: ルームウェア レディース 上下 | C9: ルームウェア | D9: 通年 | E9: S/M/L | H9: 未着手
A10: 9 | B10: 裏起毛 レギンス | C10: ボトムス | D10: 秋冬 | E10: S/M/L | H10: 未着手
A11: 10 | B11: ストール 大判 | C11: ファッション小物 | D11: 通年 | E11: フリー | H11: 未着手
A12: 11 | B12: バケットハット | C12: 帽子 | D12: 春夏 | E12: フリー | H12: 未着手
A13: 12 | B13: 冷感 アームカバー | C13: UV小物 | D13: 春夏 | E13: フリー | H13: 未着手
A14: 13 | B14: ヘアバンド 洗顔 | C14: ヘアアクセ | D14: 通年 | E14: フリー | H14: 未着手
... A19: 18 | B19: 5本指ソックス | C19: 靴下 | D19: 通年 | E19: フリー | H19: 未着手
B51: ※キーワードは案です。季節が合うもの・フリーサイズのものから始めるのがおすすめ。

Sheet セラーリスト
A1: No | B1: 見つけたキーワード | C1: セラー名 | D1: ストアURL | E1: ブランド名 | F1: 所在地 | G1: 中国セラー？ | H1: 商品数 | I1: 評価数 | J1: 高評価率 | K1: 主なカテゴリ | L1: 価格帯 | M1: 注目度 | N1: 確認日 | O1: メモ
A2: 1 | B2: ネックウォーマー 裏起毛 | C2: Andeor【公式直営店】 | D2: https://www.amazon.co.jp/gp/help/seller/at-a-glance.html/ref=dp_merchant_link?seller=A24PQELGGN47G0 | E2: Andeor | F2: 深圳市 518100 CN | G2: はい | K2: ネックウォーマー | L2: 1,880円 | M2: A | N2: 2026/10/12 | O2: この検索に1商品／推定月販計618個／商品レビュー最大1437件
A3: 2 | B3: ネックウォーマー 裏起毛 | C3: Bafup JP-amz | D3: https://www.amazon.co.jp/gp/help/seller/at-a-glance.html/ref=dp_merchant_link?seller=A2X35YNORZ18SB | E3: Bafup | F3: 深圳市 518100 CN | G3: はい | K3: ネックウォーマー | L3: 1,180円 | M3: A | N3: 2026/10/12 | O3: この検索に1商品／推定月販計433個／商品レビュー最大2258件
A4: 3 | B4: ネックウォーマー 裏起毛 | C4: ロックブロス | D4: https://www.amazon.co.jp/gp/help/seller/at-a-glance.html/ref=dp_merchant_link?seller=A11O46POEXFW30 | E4: ROCKBROS | F4: Hangzhou Zhejiang 310011 CN | G4: はい | K4: ネックウォーマー | L4: 1,699円 | M4: A | N4: 2026/10/12 | O4: この検索に2商品／推定月販計421個／商品レビュー最大2229件
A5: 4 | B5: ネックウォーマー 裏起毛 | C5: AOY直営店 | D5: https://www.amazon.co.jp/gp/help/seller/at-a-glance.html/ref=dp_merchant_link?seller=A2QUCV77L8PD8L | E5: AOY | F5: 朝阳市 辽宁 122400 CN | G5: はい | K5: ネックウォーマー | L5: 999〜1,680円 | M5: A | N5: 2026/10/12 | O5: この検索に3商品／推定月販計312個／商品レビュー最大972件
A6: 5 | B6: ネックウォーマー 裏起毛 | C6: 自由鸟 | D6: https://www.amazon.co.jp/gp/help/seller/at-a-glance.html/ref=dp_merchant_link?seller=AGH9C6511NTEG | E6: ShinHye | F6: 金华市义乌市 浙江省 322000 CN | G6: はい | K6: ネックウォーマー | L6: 1,599円 | M6: A | N6: 2026/10/12 | O6: この検索に1商品／推定月販計304個／商品レビュー最大589件
A7: 6 | B7: ネックウォーマー 裏起毛 | C7: MayCherry Classique | D7: https://www.amazon.co.jp/gp/help/seller/at-a-glance.html/ref=dp_merchant_link?seller=A1406E3VTP3PVR | E7: MayCherry | F7: 武汉市 湖北 430050 CN | G7: はい | K7: ネックウォーマー | L7: 1,580円 | M7: A | N7: 2026/10/12 | O7: この検索に1商品／推定月販計242個／商品レビュー最大192件
A8: 7 | B8: ネックウォーマー 裏起毛 | C8: EAXGO JP【公式オンラインストア】 | D8: https://www.amazon.co.jp/gp/help/seller/at-a-glance.html/ref=dp_merchant_link?seller=A8LJG87MP5ZV7 | E8: EAXGO | F8: 株洲市 湖南省 412500 CN | G8: はい | K8: ネックウォーマー | L8: 1,280円 | M8: A | N8: 2026/10/12 | O8: この検索に1商品／推定月販計197個／商品レビュー最大368件
A9: 8 | B9: ネックウォーマー 裏起毛 | C9: HORADON（ホラドン）Store【30日返金保証付き！】 | D9: https://www.amazon.co.jp/gp/help/seller/at-a-glance.html/ref=dp_merchant_link?seller=A18KZ1ZWLCQ9AD | E9: HORADON | F9: 深圳市 518100 CN | G9: はい | K9: ネックウォーマー | L9: 1,180円 | M9: A | N9: 2026/10/12 | O9: この検索に1商品／推定月販計162個／商品レビュー最大214件
A10: 9 | B10: ネックウォーマー 裏起毛 | C10: Velaci【公式販売店】 | D10: https://www.amazon.co.jp/gp/help/seller/at-a-glance.html/ref=dp_merchant_link?seller=A2V2UM8L5TD0G2 | E10: Velaci | F10: 深圳市 518100 CN | G10: はい | K10: ネックウォーマー | L10: 999円 | M10: A | N10: 2026/10/12 | O10: この検索に1商品／推定月販計153個／商品レビュー最大102件
A11: 10 | B11: ネックウォーマー 裏起毛 | C11: MOWO-japan | D11: https://www.amazon.co.jp/gp/help/seller/at-a-glance.html/ref=dp_merchant_link?seller=A3HCMCYLM6CWOR | E11: MOWO | F11: 东莞市 广东省 523000 CN | G11: はい | K11: ネックウォーマー | L11: 1,280円 | M11: B | N11: 2026/10/12 | O11: この検索に1商品／推定月販計127個／商品レビュー最大15件
A12: 11 | B12: ネックウォーマー 裏起毛 | C12: PALAME【公式ショップ】 | D12: https://www.amazon.co.jp/gp/help/seller/at-a-glance.html/ref=dp_merchant_link?seller=A1XLO99YFRJT6A | E12: PALAME | F12: 广州市 广东 510900 CN | G12: はい | K12: ネックウォーマー | L12: 999〜1,580円 | M12: B | N12: 2026/10/12 | O12: この検索に3商品／推定月販計115個／商品レビュー最大202件
A13: 12 | B13: ネックウォーマー 裏起毛 | C13: Qianyuanwei JP | D13: https://www.amazon.co.jp/gp/help/seller/at-a-glance.html/ref=dp_merchant_link?seller=A50JKETHI8XZ3 | E13: Freeluck | F13: 武汉市 湖北省 430299 CN | G13: はい | K13: ネックウォーマー | L13: 1,980円 | M13: B | N13: 2026/10/12 | O13: この検索に1商品／推定月販計112個／商品レビュー最大476件
... A30: 29 | B30: ネックウォーマー 裏起毛 | C30: SOWAN | D30: https://www.amazon.co.jp/gp/help/seller/at-a-glance.html/ref=dp_merchant_link?seller=A28Y5IGKR4VA2E | E30: SOWAN | F30: 加古川市 兵庫県 6750332 JP | G30: いいえ | K30: ネックウォーマー | L30: 2,035円 | M30: C | N30: 2026/10/12 | O30: この検索に1商品／推定月販計2個／商品レビュー最大-件
A31: 30 | B31: ネックウォーマー 裏起毛 | C31: BarryExquisiteGoods | D31: https://www.amazon.co.jp/gp/help/seller/at-a-glance.html/ref=dp_merchant_link?seller=AS2SM8GKY94NJ | E31: Taigu | G31: たぶん | K31: ネックウォーマー | L31: 1,380円 | M31: B | N31: 2026/10/12 | O31: この検索に1商品／推定月販計0個／商品レビュー最大-件／所在地データなし→セラーページで要確認
A32: 31 | B32: ネックウォーマー 裏起毛 | C32: Kuijidianzi JP | D32: https://www.amazon.co.jp/gp/help/seller/at-a-glance.html/ref=dp_merchant_link?seller=AXTCIRN2YHZ49 | E32: Sungale | G32: たぶん | K32: ネックウォーマー | L32: 1,980円 | M32: B | N32: 2026/10/12 | O32: この検索に1商品／推定月販計0個／商品レビュー最大-件／所在地データなし→セラーページで要確認
A33: 32 | B33: ネックウォーマー 裏起毛 | C33: Ruiyaa | D33: https://www.amazon.co.jp/gp/help/seller/at-a-glance.html/ref=dp_merchant_link?seller=A3F6AJ6LP7DWJ9 | E33: GEMAKA | G33: たぶん | K33: ネックウォーマー | L33: 599円 | M33: B | N33: 2026/10/12 | O33: この検索に1商品／推定月販計0個／商品レビュー最大4件／所在地データなし→セラーページで要確認
A34: 33 | B34: ネックウォーマー 裏起毛 | C34: Pneito JP | D34: https://www.amazon.co.jp/gp/help/seller/at-a-glance.html/ref=dp_merchant_link?seller=A3U3I24JQ306RH | E34: Pneito | G34: たぶん | K34: ネックウォーマー | L34: 1,280円 | M34: B | N34: 2026/10/12 | O34: この検索に1商品／推定月販計0個／商品レビュー最大117件／所在地データなし→セラーページで要確認
A35: 34 | B35: ネックウォーマー 裏起毛 | C35: LAAVVA専門店・日本の中小企業 | D35: https://www.amazon.co.jp/gp/help/seller/at-a-glance.html/ref=dp_merchant_link?seller=A3W0KOEQENONIV | E35: LAAVVA | G35: たぶん | K35: ネックウォーマー | L35: 1,155円 | M35: B | N35: 2026/10/12 | O35: この検索に1商品／推定月販計0個／商品レビュー最大30件／所在地データなし→セラーページで要確認
A36: 35 | B36: ネックウォーマー 裏起毛 | C36: LEXINZHI | D36: https://www.amazon.co.jp/gp/help/seller/at-a-glance.html/ref=dp_merchant_link?seller=A1EZCM6C7ZAMWC | E36: DELUXEFOX | G36: たぶん | K36: ネックウォーマー | L36: 679円 | M36: B | N36: 2026/10/12 | O36: この検索に1商品／推定月販計0個／商品レビュー最大2件／所在地データなし→セラーページで要確認
A37: 36 | B37: ネックウォーマー 裏起毛 | C37: E-Reise | D37: https://www.amazon.co.jp/gp/help/seller/at-a-glance.html/ref=dp_merchant_link?seller=A17NRKXL7A8NVA | E37: E-Reise | G37: たぶん | K37: ネックウォーマー | L37: 749円 | M37: B | N37: 2026/10/12 | O37: この検索に1商品／推定月販計0個／商品レビュー最大27件／所在地データなし→セラーページで要確認
A38: 37 | B38: ネックウォーマー 裏起毛 | C38: Wild Scene | D38: https://www.amazon.co.jp/gp/help/seller/at-a-glance.html/ref=dp_merchant_link?seller=A1CXRM8486SKGE | E38: Wild Scene | G38: たぶん | K38: ネックウォーマー | L38: 1,680円 | M38: B | N38: 2026/10/12 | O38: この検索に1商品／推定月販計0個／商品レビュー最大297件／所在地データなし→セラーページで要確認
A39: 38 | B39: ネックウォーマー 裏起毛 | C39: 【公式】AWASEYY | D39: https://www.amazon.co.jp/gp/help/seller/at-a-glance.html/ref=dp_merchant_link?seller=A14RGXN343LE8Z | E39: AWASEYY | G39: たぶん | K39: ネックウォーマー | L39: 750円 | M39: B | N39: 2026/10/12 | O39: この検索に1商品／推定月販計0個／商品レビュー最大543件／所在地データなし→セラーページで要確認
A40: 39 | B40: ネックウォーマー 裏起毛 | C40: ZVCXOE-JP | D40: https://www.amazon.co.jp/gp/help/seller/at-a-glance.html/ref=dp_merchant_link?seller=A3DI4EG5TIMDOG | E40: ZVCXOE | F40: Pingshan District | G40: はい | K40: ネックウォーマー | L40: 999円 | M40: B | N40: 2026/10/12 | O40: この検索に1商品／推定月販計0個／商品レビュー最大10件
A41: =IF(C41="","",ROW()-1)
A42: =IF(C42="","",ROW()-1)
A43: =IF(C43="","",ROW()-1)
A44: =IF(C44="","",ROW()-1)
A45: =IF(C45="","",ROW()-1)
A46: =IF(C46="","",ROW()-1)
A47: =IF(C47="","",ROW()-1)
A48: =IF(C48="","",ROW()-1)
A49: =IF(C49="","",ROW()-1)
A50: =IF(C50="","",ROW()-1)
A51: =IF(C51="","",ROW()-1)
A52: =IF(C52="","",ROW()-1)
... A201: =IF(C201="","",ROW()-1)

Sheet 商品候補
A1: No | B1: セラー名 | C1: ブランド名 | D1: 商品名（短く） | E1: ASIN | F1: 商品URL | G1: 価格（円） | H1: BSR（ランキング） | I1: BSRのカテゴリ | J1: レビュー数 | K1: 星評価 | L1: 推定月販（個） | M1: 色・サイズ数 | N1: 改良アイデア | O1: 調査キーワード | P1: ライバル判定 | Q1: 最終判断 | R1: メモ
A2: 1 | B2: Andeor【公式直営店】 | C2: Andeor | D2: ネックウォーマー メンズ 冬 防寒 【360°極めた暖かさ・柔らかい肌触り・調節 | E2: B0BDD4SW12 | F2: https://www.amazon.co.jp/dp/B0BDD4SW12 | G2: 1880 | H2: 1 | I2: メンズネックウォーマー | J2: 1437 | K2: 4.6 | L2: 618 | M2: 20 | O2: ネックウォーマー 裏起毛 | P2: =IF(O2="","",IFERROR(INDEX(ライバル調査!$K:$K,MATCH(O2,ライバル調査!$B:$B,0)),"未調査")) -> △ 要検討 | R2: 出品日 2022-09-08／自然順位：第1ページ3
A3: 2 | B3: Bafup JP-amz | C3: Bafup | D3: 【新色追加！】ネックウォーマー ネックガード 冬 極めた暖かさ ふわふわ裏起毛 | E3: B08RN6418Y | F3: https://www.amazon.co.jp/dp/B08RN6418Y | G3: 1180 | H3: 2 | I3: レディースネックウォーマー メンズネックウォーマー | J3: 2258 | K3: 4.6 | L3: 433 | M3: 38 | O3: ネックウォーマー 裏起毛 | P3: =IF(O3="","",IFERROR(INDEX(ライバル調査!$K:$K,MATCH(O3,ライバル調査!$B:$B,0)),"未調査")) -> △ 要検討 | R3: 出品日 2021-01-17／自然順位：第1ページ28
A4: 3 | B4: ロックブロス | C4: ROCKBROS | D4: ROCKBROS バラクラバ ネックウォーマー 冬用 防寒 目出し帽 裏起毛 防 | E4: B0CKNBY5Z6 | F4: https://www.amazon.co.jp/dp/B0CKNBY5Z6 | G4: 1699 | H4: 12 | I4: メンズサイクリングハット・帽子 | J4: 2229 | K4: 4.3 | L4: 404 | M4: 4 | O4: ネックウォーマー 裏起毛 | P4: =IF(O4="","",IFERROR(INDEX(ライバル調査!$K:$K,MATCH(O4,ライバル調査!$B:$B,0)),"未調査")) -> △ 要検討 | R4: 出品日 2023-10-08／自然順位：第1ページ17
A5: 4 | B5: 自由鸟 | C5: ShinHye | D5: バラクラバ 冬用 裏起毛 防寒 防風 ネックウォーマー メガネホール 反射ロゴ | E5: B0FQ5QJSXJ | F5: https://www.amazon.co.jp/dp/B0FQ5QJSXJ | G5: 1599 | H5: 3 | I5: メンズ目出し帽 | J5: 589 | K5: 4.2 | L5: 304 | M5: 8 | N5: 【不満】薄い・息で濡れて冷える・首がぶかぶか・写真と違う・61cm表記なのに小さい。【改良】厚手の裏起毛＋口元に吸湿速乾素材、ドローコードで首元調整、実物どおりの写真と正確な寸法表 | O5: ネックウォーマー 裏起毛 | P5: =IF(O5="","",IFERROR(INDEX(ライバル調査!$K:$K,MATCH(O5,ライバル調査!$B:$B,0)),"未調査")) -> △ 要検討 | R5: 出品日 2025-09-26／自然順位：第1ページ25
A6: 5 | B6: MayCherry Classique | C6: MayCherry | D6: バラクラバ ネックウォーマー 防寒 冬用 爆熱零下保温 極厚裏起毛 帽子 目出し | E6: B0FT285DG9 | F6: https://www.amazon.co.jp/dp/B0FT285DG9 | G6: 1580 | H6: 2 | I6: メンズ目出し帽 | J6: 192 | K6: 4.4 | L6: 242 | M6: 5 | N6: 【不満】首の丈が短い・フードが小さく帽子の上から被れない・髪がつぶれる・糸くず/ゴミ/圧縮シワ（検品不足）。【改良】首の丈を長く、フードにゆとり、検品とたたみ梱包 | O6: ネックウォーマー 裏起毛 | P6: =IF(O6="","",IFERROR(INDEX(ライバル調査!$K:$K,MATCH(O6,ライバル調査!$B:$B,0)),"未調査")) -> △ 要検討 | R6: 出品日 2025-09-29／自然順位：第1ページ6
A7: 6 | B7: AOY直営店 | C7: AOY | D7: ネックウォーマー メンズ かつてない着け心地 裏ボア 小顔に見える | E7: B0BJV9C924 | F7: https://www.amazon.co.jp/dp/B0BJV9C924 | G7: 999 | H7: 11 | I7: メンズネックウォーマー | J7: 972 | K7: 4.5 | L7: 198 | M7: 17 | O7: ネックウォーマー 裏起毛 | P7: =IF(O7="","",IFERROR(INDEX(ライバル調査!$K:$K,MATCH(O7,ライバル調査!$B:$B,0)),"未調査")) -> △ 要検討 | R7: 出品日 2022-11-04／自然順位：第1ページ2
A8: 7 | B8: EAXGO JP【公式オンラインストア】 | C8: EAXGO | D8: ネックウォーマー メンズ レディース 防寒 防風 スキー 裏起毛 保温 暖かい | E8: B0CHRB667G | F8: https://www.amazon.co.jp/dp/B0CHRB667G | G8: 1280 | H8: 15 | I8: メンズネックウォーマー | J8: 368 | K8: 4.4 | L8: 197 | M8: 13 | O8: ネックウォーマー 裏起毛 | P8: =IF(O8="","",IFERROR(INDEX(ライバル調査!$K:$K,MATCH(O8,ライバル調査!$B:$B,0)),"未調査")) -> △ 要検討 | R8: 出品日 2023-09-19／自然順位：第1ページ5
A9: 8 | B9: HORADON（ホラドン）Store【30日返金保証付き！】 | C9: HORADON | D9: ネックウォーマー メンズ フェイスカバー 冬用 【裏起毛・軽量約60g・コンパク | E9: B0CJC82DH8 | F9: https://www.amazon.co.jp/dp/B0CJC82DH8 | G9: 1180 | H9: 16 | I9: メンズネックウォーマー | J9: 214 | K9: 4.5 | L9: 162 | M9: 6 | O9: ネックウォーマー 裏起毛 | P9: =IF(O9="","",IFERROR(INDEX(ライバル調査!$K:$K,MATCH(O9,ライバル調査!$B:$B,0)),"未調査")) -> △ 要検討 | R9: 出品日 2023-10-10／自然順位：第1ページ24
A10: 9 | B10: Velaci【公式販売店】 | C10: Velaci | D10: ネックウォーマー レディース 【耳掛け付き・息苦しくない・圧迫ゼロ】 2WAY防 | E10: B0FQJ75C6M | F10: https://www.amazon.co.jp/dp/B0FQJ75C6M | G10: 999 | H10: 6 | I10: レディースネックウォーマー | J10: 102 | K10: 4.2 | L10: 153 | M10: 5 | O10: ネックウォーマー 裏起毛 | P10: =IF(O10="","",IFERROR(INDEX(ライバル調査!$K:$K,MATCH(O10,ライバル調査!$B:$B,0)),"未調査")) -> △ 要検討 | R10: 出品日 2025-09-19／自然順位：第1ページ8
A11: 10 | B11: MOWO-japan | C11: MOWO | D11: ネックウォーマー レディース 【ふわふわ裏起毛】冬 防寒ネックウォーマー 防風防 | E11: B0HHGZX6H9 | F11: https://www.amazon.co.jp/dp/B0HHGZX6H9 | G11: 1280 | H11: 9 | I11: レディースネックウォーマー | J11: 15 | K11: 5 | L11: 127 | M11: 9 | O11: ネックウォーマー 裏起毛 | P11: =IF(O11="","",IFERROR(INDEX(ライバル調査!$K:$K,MATCH(O11,ライバル調査!$B:$B,0)),"未調査")) -> △ 要検討 | R11: 出品日 2026-09-12／自然順位：第1ページ4
A12: 11 | B12: Qianyuanwei JP | C12: Freeluck | D12: ネックウォーマー メンズ レディース ネックガード 防風防寒 秋冬 極めた暖かさ | E12: B0CPFDMHB9 | F12: https://www.amazon.co.jp/dp/B0CPFDMHB9 | G12: 1980 | H12: 14 | I12: メンズネックウォーマー | J12: 476 | K12: 4.4 | L12: 112 | M12: 1 | N12: 【不満】伸びず着脱しにくい・小さめ・鼻まで上げると息苦しい・ヘルメットに入らない。【改良】口元を立体＋通気メッシュ、伸縮素材でゆとり、頭部は薄手でヘルメット対応 | O12: ネックウォーマー 裏起毛 | P12: =IF(O12="","",IFERROR(INDEX(ライバル調査!$K:$K,MATCH(O12,ライバル調査!$B:$B,0)),"未調査")) -> △ 要検討 | R12: 出品日 2023-12-15／広告順位：第1ページ5
A13: 12 | B13: PALAME【公式ショップ】 | C13: PALAME | D13: ネックウォーマー メンズ 冬 【360°極めた暖かさ・ふわふわ蓄熱裏起毛・柔らか | E13: B0FPQNNNHM | F13: https://www.amazon.co.jp/dp/B0FPQNNNHM | G13: 999 | H13: 17 | I13: メンズネックウォーマー | J13: 202 | K13: 4.4 | L13: 86 | M13: 6 | O13: ネックウォーマー 裏起毛 | P13: =IF(O13="","",IFERROR(INDEX(ライバル調査!$K:$K,MATCH(O13,ライバル調査!$B:$B,0)),"未調査")) -> △ 要検討 | R13: 出品日 2025-09-18／自然順位：第1ページ1
A14: 13 | B14: AOY直営店 | C14: AOY | D14: ネックウォーマー メンズ 防寒 【頭から首元まで360°あったか】 フードウォー | E14: B0DJNHLYNJ | F14: https://www.amazon.co.jp/dp/B0DJNHLYNJ | G14: 1680 | H14: 50 | I14: メンズネックウォーマー | J14: 183 | K14: 4.3 | L14: 82 | M14: 5 | O14: ネックウォーマー 裏起毛 | P14: =IF(O14="","",IFERROR(INDEX(ライバル調査!$K:$K,MATCH(O14,ライバル調査!$B:$B,0)),"未調査")) -> △ 要検討 | R14: 出品日 2024-10-16／自然順位：第1ページ37
A15: 14 | B15: Yihaonet | C15: Seefox | D15: ネックウォーマー メンズ レディース 秋冬用 防寒防風 360°極めた暖かさ 厚 | E15: B0FSL3S5XZ | F15: https://www.amazon.co.jp/dp/B0FSL3S5XZ | G15: 1999 | H15: 112 | I15: メンズネックウォーマー | J15: 5 | K15: 5 | L15: 77 | M15: 4 | O15: ネックウォーマー 裏起毛 | P15: =IF(O15="","",IFERROR(INDEX(ライバル調査!$K:$K,MATCH(O15,ライバル調査!$B:$B,0)),"未調査")) -> △ 要検討 | R15: 出品日 2025-10-24／自然順位：第1ページ30
A16: 15 | B16: BOOMFLY | C16: BOOMFLY | D16: ネックウォーマー 防寒 冬用 メンズ レディース ニット 裏起毛 伸縮性 柔らか | E16: B0FQC3G5CZ | F16: https://www.amazon.co.jp/dp/B0FQC3G5CZ | G16: 980 | H16: 38 | I16: メンズネックウォーマー | J16: 155 | K16: 4.3 | L16: 65 | M16: 13 | O16: ネックウォーマー 裏起毛 | P16: =IF(O16="","",IFERROR(INDEX(ライバル調査!$K:$K,MATCH(O16,ライバル調査!$B:$B,0)),"未調査")) -> △ 要検討 | R16: 出品日 2025-10-04／自然順位：第1ページ12
A17: 16 | B17: SIVAN-専門店 | C17: SIVAN | D17: ネックウォーマー レディース メンズ 【防寒対策・柔らかふわふわ裏起毛素材 保温 | E17: B0FRZYMFJH | F17: https://www.amazon.co.jp/dp/B0FRZYMFJH | G17: 2080 | H17: 34 | I17: レディースネックウォーマー | J17: 34 | K17: 4.1 | L17: 64 | M17: 6 | O17: ネックウォーマー 裏起毛 | P17: =IF(O17="","",IFERROR(INDEX(ライバル調査!$K:$K,MATCH(O17,ライバル調査!$B:$B,0)),"未調査")) -> △ 要検討 | R17: 出品日 2025-09-29／自然順位：第1ページ9
A18: 17 | B18: Andeor 正規販売店[30日返金保証付き！] | C18: Andeor | D18: 【自転車選手が愛用】 ネックウォーマー メンズ 冬 【極暖38℃恒温・高機能断熱 | E18: B0DGKRMRT2 | F18: https://www.amazon.co.jp/dp/B0DGKRMRT2 | G18: 1580 | H18: 8 | I18: メンズネックウォーマー | J18: 416 | K18: 4.4 | L18: 50 | M18: 11 | O18: ネックウォーマー 裏起毛 | P18: =IF(O18="","",IFERROR(INDEX(ライバル調査!$K:$K,MATCH(O18,ライバル調査!$B:$B,0)),"未調査")) -> △ 要検討 | R18: 出品日 2024-09-10／自然順位：第1ページ46
A19: =IF(D19="","",ROW()-1) | P19: =IF(O19="","",IFERROR(INDEX(ライバル調査!$K:$K,MATCH(O19,ライバル調査!$B:$B,0)),"未調査"))
A20: =IF(D20="","",ROW()-1) | P20: =IF(O20="","",IFERROR(INDEX(ライバル調査!$K:$K,MATCH(O20,ライバル調査!$B:$B,0)),"未調査"))
A21: =IF(D21="","",ROW()-1) | P21: =IF(O21="","",IFERROR(INDEX(ライバル調査!$K:$K,MATCH(O21,ライバル調査!$B:$B,0)),"未調査"))
A22: =IF(D22="","",ROW()-1) | P22: =IF(O22="","",IFERROR(INDEX(ライバル調査!$K:$K,MATCH(O22,ライバル調査!$B:$B,0)),"未調査"))
A23: =IF(D23="","",ROW()-1) | P23: =IF(O23="","",IFERROR(INDEX(ライバル調査!$K:$K,MATCH(O23,ライバル調査!$B:$B,0)),"未調査"))
A24: =IF(D24="","",ROW()-1) | P24: =IF(O24="","",IFERROR(INDEX(ライバル調査!$K:$K,MATCH(O24,ライバル調査!$B:$B,0)),"未調査"))
A25: =IF(D25="","",ROW()-1) | P25: =IF(O25="","",IFERROR(INDEX(ライバル調査!$K:$K,MATCH(O25,ライバル調査!$B:$B,0)),"未調査"))
A26: =IF(D26="","",ROW()-1) | P26: =IF(O26="","",IFERROR(INDEX(ライバル調査!$K:$K,MATCH(O26,ライバル調査!$B:$B,0)),"未調査"))
A27: =IF(D27="","",ROW()-1) | P27: =IF(O27="","",IFERROR(INDEX(ライバル調査!$K:$K,MATCH(O27,ライバル調査!$B:$B,0)),"未調査"))
A28: =IF(D28="","",ROW()-1) | P28: =IF(O28="","",IFERROR(INDEX(ライバル調査!$K:$K,MATCH(O28,ライバル調査!$B:$B,0)),"未調査"))
A29: =IF(D29="","",ROW()-1) | P29: =IF(O29="","",IFERROR(INDEX(ライバル調査!$K:$K,MATCH(O29,ライバル調査!$B:$B,0)),"未調査"))
A30: =IF(D30="","",ROW()-1) | P30: =IF(O30="","",IFERROR(INDEX(ライバル調査!$K:$K,MATCH(O30,ライバル調査!$B:$B,0)),"未調査"))
... A201: =IF(D201="","",ROW()-1) | P201: =IF(O201="","",IFERROR(INDEX(ライバル調査!$K:$K,MATCH(O201,ライバル調査!$B:$B,0)),"未調査"))

Sheet 上位10件データ
A1: キーワード | B1: 順位 | C1: ASIN | D1: 商品名（短く） | E1: 価格（円） | F1: レビュー数 | G1: 推定月販（個） | H1: 中国セラー？ | I1: メモ
A2: ネックウォーマー 裏起毛 | B2: 1 | C2: B0FPQNNNHM | D2: [PALAME] ネックウォーマー メンズ 冬 【360°極めた暖かさ・ふわふ | E2: 999 | F2: 202 | G2: 86 | H2: はい | I2: 自然順位1
A3: ネックウォーマー 裏起毛 | B3: 2 | C3: B0BJV9C924 | D3: [AOY] ネックウォーマー メンズ かつてない着け心地 裏ボア 小顔に | E3: 999 | F3: 972 | G3: 198 | H3: はい | I3: 自然順位2
A4: ネックウォーマー 裏起毛 | B4: 3 | C4: B0BDD4SW12 | D4: [Andeor] ネックウォーマー メンズ 冬 防寒 【360°極めた暖かさ・ | E4: 1880 | F4: 1437 | G4: 618 | H4: はい | I4: 自然順位3
A5: ネックウォーマー 裏起毛 | B5: 4 | C5: B0HHGZX6H9 | D5: [MOWO] ネックウォーマー レディース 【ふわふわ裏起毛】冬 防寒ネッ | E5: 1280 | F5: 15 | G5: 127 | H5: はい | I5: 自然順位4
A6: ネックウォーマー 裏起毛 | B6: 5 | C6: B0CHRB667G | D6: [EAXGO] ネックウォーマー メンズ レディース 防寒 防風 スキー 裏 | E6: 1280 | F6: 368 | G6: 197 | H6: はい | I6: 自然順位5
A7: ネックウォーマー 裏起毛 | B7: 6 | C7: B0FT285DG9 | D7: [MayCherry] バラクラバ ネックウォーマー 防寒 冬用 爆熱零下保温 極厚 | E7: 1580 | F7: 192 | G7: 242 | H7: はい | I7: 自然順位6
A8: ネックウォーマー 裏起毛 | B8: 7 | C8: B0DD7C8WX5 | D8: [Petasonien] ネックウォーマー メンズ レディース 冬 防寒防風 暖かい | E8: 1780 | F8: 261 | H8: はい | I8: 自然順位7
A9: ネックウォーマー 裏起毛 | B9: 8 | C9: B0FQJ75C6M | D9: [Velaci] ネックウォーマー レディース 【耳掛け付き・息苦しくない・圧 | E9: 999 | F9: 102 | G9: 153 | H9: はい | I9: 自然順位8
A10: ネックウォーマー 裏起毛 | B10: 9 | C10: B0FRZYMFJH | D10: [SIVAN] ネックウォーマー レディース メンズ 【防寒対策・柔らかふわ | E10: 2080 | F10: 34 | G10: 64 | H10: はい | I10: 自然順位9
A11: ネックウォーマー 裏起毛 | B11: 10 | C11: B0HKS9LRY4 | D11: [Taigu] ネックウォーマー ボタン付き レディース メンズ 防寒 秋冬 | E11: 1380 | H11: たぶん | I11: 自然順位10

Sheet ライバル調査
A1: No | B1: キーワード | C1: 検索結果数 | D1: 入力件数 | E1: 平均月販 | F1: 合計月販 | G1: 平均価格 | H1: 強者数（レビュー1000+） | I1: 新規枠（レビュー100未満） | J1: 合格数（5項目中） | K1: 判定 | L1: 需要 | M1: 強者 | N1: 新規枠 | O1: 価格 | P1: 中国セラー率 | Q1: メモ
A2: =IF(B2="","",ROW()-1) -> 1 | B2: ネックウォーマー 裏起毛 | D2: =IF(B2="","",COUNTIFS(上位10件データ!$A:$A,$B2)) -> 10 | E2: =IF(OR(B2="",D2=0),"",AVERAGEIFS(上位10件データ!$G:$G,上位10件データ!$A:$A,$B2)) -> 210.625 | F2: =IF(OR(B2="",D2=0),"",SUMIFS(上位10件データ!$G:$G,上位10件データ!$A:$A,$B2)) -> 1685 | G2: =IF(OR(B2="",D2=0),"",AVERAGEIFS(上位10件データ!$E:$E,上位10件データ!$A:$A,$B2)) -> 1425.7 | H2: =IF(OR(B2="",D2=0),"",COUNTIFS(上位10件データ!$A:$A,$B2,上位10件データ!$F:$F,">=1000")) -> 1 | I2: =IF(OR(B2="",D2=0),"",COUNTIFS(上位10件データ!$A:$A,$B2,上位10件データ!$F:$F,"<100")) -> 2 | J2: =IF(E2="","",COUNTIF(L2:O2,"○")+IF(P2>=0.5,1,0)) -> 3 | K2: =IF(J2="","",IF(J2>=設定!$B$19,"◎ 有力",IF(J2>=設定!$B$20,"○ 候補",IF(J2>=3,"△ 要検討","× 見送り")))) -> △ 要検討 | L2: =IF(E2="","",IF(E2>=設定!$B$14,"○","×")) -> ○ | M2: =IF(H2="","",IF(H2<=設定!$B$15,"○","×")) -> ○ | N2: =IF(I2="","",IF(I2>=設定!$B$16,"○","×")) -> × | O2: =IF(G2="","",IF(AND(G2>=設定!$B$17,G2<=設定!$B$18),"○","×")) -> × | P2: =IF(OR(B2="",D2=0),"",COUNTIFS(上位10件データ!$A:$A,$B2,上位10件データ!$H:$H,"はい")/D2) -> 0.9 | Q2: SellerSprite出力(10/12)より。検索結果の約9割が中国セラー
A3: =IF(B3="","",ROW()-1) | D3: =IF(B3="","",COUNTIFS(上位10件データ!$A:$A,$B3)) | E3: =IF(OR(B3="",D3=0),"",AVERAGEIFS(上位10件データ!$G:$G,上位10件データ!$A:$A,$B3)) | F3: =IF(OR(B3="",D3=0),"",SUMIFS(上位10件データ!$G:$G,上位10件データ!$A:$A,$B3)) | G3: =IF(OR(B3="",D3=0),"",AVERAGEIFS(上位10件データ!$E:$E,上位10件データ!$A:$A,$B3)) | H3: =IF(OR(B3="",D3=0),"",COUNTIFS(上位10件データ!$A:$A,$B3,上位10件データ!$F:$F,">=1000")) | I3: =IF(OR(B3="",D3=0),"",COUNTIFS(上位10件データ!$A:$A,$B3,上位10件データ!$F:$F,"<100")) | J3: =IF(E3="","",COUNTIF(L3:O3,"○")+IF(P3>=0.5,1,0)) | K3: =IF(J3="","",IF(J3>=設定!$B$19,"◎ 有力",IF(J3>=設定!$B$20,"○ 候補",IF(J3>=3,"△ 要検討","× 見送り")))) | L3: =IF(E3="","",IF(E3>=設定!$B$14,"○","×")) | M3: =IF(H3="","",IF(H3<=設定!$B$15,"○","×")) | N3: =IF(I3="","",IF(I3>=設定!$B$16,"○","×")) | O3: =IF(G3="","",IF(AND(G3>=設定!$B$17,G3<=設定!$B$18),"○","×")) | P3: =IF(OR(B3="",D3=0),"",COUNTIFS(上位10件データ!$A:$A,$B3,上位10件データ!$H:$H,"はい")/D3)
A4: =IF(B4="","",ROW()-1) | D4: =IF(B4="","",COUNTIFS(上位10件データ!$A:$A,$B4)) | E4: =IF(OR(B4="",D4=0),"",AVERAGEIFS(上位10件データ!$G:$G,上位10件データ!$A:$A,$B4)) | F4: =IF(OR(B4="",D4=0),"",SUMIFS(上位10件データ!$G:$G,上位10件データ!$A:$A,$B4)) | G4: =IF(OR(B4="",D4=0),"",AVERAGEIFS(上位10件データ!$E:$E,上位10件データ!$A:$A,$B4)) | H4: =IF(OR(B4="",D4=0),"",COUNTIFS(上位10件データ!$A:$A,$B4,上位10件データ!$F:$F,">=1000")) | I4: =IF(OR(B4="",D4=0),"",COUNTIFS(上位10件データ!$A:$A,$B4,上位10件データ!$F:$F,"<100")) | J4: =IF(E4="","",COUNTIF(L4:O4,"○")+IF(P4>=0.5,1,0)) | K4: =IF(J4="","",IF(J4>=設定!$B$19,"◎ 有力",IF(J4>=設定!$B$20,"○ 候補",IF(J4>=3,"△ 要検討","× 見送り")))) | L4: =IF(E4="","",IF(E4>=設定!$B$14,"○","×")) | M4: =IF(H4="","",IF(H4<=設定!$B$15,"○","×")) | N4: =IF(I4="","",IF(I4>=設定!$B$16,"○","×")) | O4: =IF(G4="","",IF(AND(G4>=設定!$B$17,G4<=設定!$B$18),"○","×")) | P4: =IF(OR(B4="",D4=0),"",COUNTIFS(上位10件データ!$A:$A,$B4,上位10件データ!$H:$H,"はい")/D4)
A5: =IF(B5="","",ROW()-1) | D5: =IF(B5="","",COUNTIFS(上位10件データ!$A:$A,$B5)) | E5: =IF(OR(B5="",D5=0),"",AVERAGEIFS(上位10件データ!$G:$G,上位10件データ!$A:$A,$B5)) | F5: =IF(OR(B5="",D5=0),"",SUMIFS(上位10件データ!$G:$G,上位10件データ!$A:$A,$B5)) | G5: =IF(OR(B5="",D5=0),"",AVERAGEIFS(上位10件データ!$E:$E,上位10件データ!$A:$A,$B5)) | H5: =IF(OR(B5="",D5=0),"",COUNTIFS(上位10件データ!$A:$A,$B5,上位10件データ!$F:$F,">=1000")) | I5: =IF(OR(B5="",D5=0),"",COUNTIFS(上位10件データ!$A:$A,$B5,上位10件データ!$F:$F,"<100")) | J5: =IF(E5="","",COUNTIF(L5:O5,"○")+IF(P5>=0.5,1,0)) | K5: =IF(J5="","",IF(J5>=設定!$B$19,"◎ 有力",IF(J5>=設定!$B$20,"○ 候補",IF(J5>=3,"△ 要検討","× 見送り")))) | L5: =IF(E5="","",IF(E5>=設定!$B$14,"○","×")) | M5: =IF(H5="","",IF(H5<=設定!$B$15,"○","×")) | N5: =IF(I5="","",IF(I5>=設定!$B$16,"○","×")) | O5: =IF(G5="","",IF(AND(G5>=設定!$B$17,G5<=設定!$B$18),"○","×")) | P5: =IF(OR(B5="",D5=0),"",COUNTIFS(上位10件データ!$A:$A,$B5,上位10件データ!$H:$H,"はい")/D5)
A6: =IF(B6="","",ROW()-1) | D6: =IF(B6="","",COUNTIFS(上位10件データ!$A:$A,$B6)) | E6: =IF(OR(B6="",D6=0),"",AVERAGEIFS(上位10件データ!$G:$G,上位10件データ!$A:$A,$B6)) | F6: =IF(OR(B6="",D6=0),"",SUMIFS(上位10件データ!$G:$G,上位10件データ!$A:$A,$B6)) | G6: =IF(OR(B6="",D6=0),"",AVERAGEIFS(上位10件データ!$E:$E,上位10件データ!$A:$A,$B6)) | H6: =IF(OR(B6="",D6=0),"",COUNTIFS(上位10件データ!$A:$A,$B6,上位10件データ!$F:$F,">=1000")) | I6: =IF(OR(B6="",D6=0),"",COUNTIFS(上位10件データ!$A:$A,$B6,上位10件データ!$F:$F,"<100")) | J6: =IF(E6="","",COUNTIF(L6:O6,"○")+IF(P6>=0.5,1,0)) | K6: =IF(J6="","",IF(J6>=設定!$B$19,"◎ 有力",IF(J6>=設定!$B$20,"○ 候補",IF(J6>=3,"△ 要検討","× 見送り")))) | L6: =IF(E6="","",IF(E6>=設定!$B$14,"○","×")) | M6: =IF(H6="","",IF(H6<=設定!$B$15,"○","×")) | N6: =IF(I6="","",IF(I6>=設定!$B$16,"○","×")) | O6: =IF(G6="","",IF(AND(G6>=設定!$B$17,G6<=設定!$B$18),"○","×")) | P6: =IF(OR(B6="",D6=0),"",COUNTIFS(上位10件データ!$A:$A,$B6,上位10件データ!$H:$H,"はい")/D6)
A7: =IF(B7="","",ROW()-1) | D7: =IF(B7="","",COUNTIFS(上位10件データ!$A:$A,$B7)) | E7: =IF(OR(B7="",D7=0),"",AVERAGEIFS(上位10件データ!$G:$G,上位10件データ!$A:$A,$B7)) | F7: =IF(OR(B7="",D7=0),"",SUMIFS(上位10件データ!$G:$G,上位10件データ!$A:$A,$B7)) | G7: =IF(OR(B7="",D7=0),"",AVERAGEIFS(上位10件データ!$E:$E,上位10件データ!$A:$A,$B7)) | H7: =IF(OR(B7="",D7=0),"",COUNTIFS(上位10件データ!$A:$A,$B7,上位10件データ!$F:$F,">=1000")) | I7: =IF(OR(B7="",D7=0),"",COUNTIFS(上位10件データ!$A:$A,$B7,上位10件データ!$F:$F,"<100")) | J7: =IF(E7="","",COUNTIF(L7:O7,"○")+IF(P7>=0.5,1,0)) | K7: =IF(J7="","",IF(J7>=設定!$B$19,"◎ 有力",IF(J7>=設定!$B$20,"○ 候補",IF(J7>=3,"△ 要検討","× 見送り")))) | L7: =IF(E7="","",IF(E7>=設定!$B$14,"○","×")) | M7: =IF(H7="","",IF(H7<=設定!$B$15,"○","×")) | N7: =IF(I7="","",IF(I7>=設定!$B$16,"○","×")) | O7: =IF(G7="","",IF(AND(G7>=設定!$B$17,G7<=設定!$B$18),"○","×")) | P7: =IF(OR(B7="",D7=0),"",COUNTIFS(上位10件データ!$A:$A,$B7,上位10件データ!$H:$H,"はい")/D7)
A8: =IF(B8="","",ROW()-1) | D8: =IF(B8="","",COUNTIFS(上位10件データ!$A:$A,$B8)) | E8: =IF(OR(B8="",D8=0),"",AVERAGEIFS(上位10件データ!$G:$G,上位10件データ!$A:$A,$B8)) | F8: =IF(OR(B8="",D8=0),"",SUMIFS(上位10件データ!$G:$G,上位10件データ!$A:$A,$B8)) | G8: =IF(OR(B8="",D8=0),"",AVERAGEIFS(上位10件データ!$E:$E,上位10件データ!$A:$A,$B8)) | H8: =IF(OR(B8="",D8=0),"",COUNTIFS(上位10件データ!$A:$A,$B8,上位10件データ!$F:$F,">=1000")) | I8: =IF(OR(B8="",D8=0),"",COUNTIFS(上位10件データ!$A:$A,$B8,上位10件データ!$F:$F,"<100")) | J8: =IF(E8="","",COUNTIF(L8:O8,"○")+IF(P8>=0.5,1,0)) | K8: =IF(J8="","",IF(J8>=設定!$B$19,"◎ 有力",IF(J8>=設定!$B$20,"○ 候補",IF(J8>=3,"△ 要検討","× 見送り")))) | L8: =IF(E8="","",IF(E8>=設定!$B$14,"○","×")) | M8: =IF(H8="","",IF(H8<=設定!$B$15,"○","×")) | N8: =IF(I8="","",IF(I8>=設定!$B$16,"○","×")) | O8: =IF(G8="","",IF(AND(G8>=設定!$B$17,G8<=設定!$B$18),"○","×")) | P8: =IF(OR(B8="",D8=0),"",COUNTIFS(上位10件データ!$A:$A,$B8,上位10件データ!$H:$H,"はい")/D8)
A9: =IF(B9="","",ROW()-1) | D9: =IF(B9="","",COUNTIFS(上位10件データ!$A:$A,$B9)) | E9: =IF(OR(B9="",D9=0),"",AVERAGEIFS(上位10件データ!$G:$G,上位10件データ!$A:$A,$B9)) | F9: =IF(OR(B9="",D9=0),"",SUMIFS(上位10件データ!$G:$G,上位10件データ!$A:$A,$B9)) | G9: =IF(OR(B9="",D9=0),"",AVERAGEIFS(上位10件データ!$E:$E,上位10件データ!$A:$A,$B9)) | H9: =IF(OR(B9="",D9=0),"",COUNTIFS(上位10件データ!$A:$A,$B9,上位10件データ!$F:$F,">=1000")) | I9: =IF(OR(B9="",D9=0),"",COUNTIFS(上位10件データ!$A:$A,$B9,上位10件データ!$F:$F,"<100")) | J9: =IF(E9="","",COUNTIF(L9:O9,"○")+IF(P9>=0.5,1,0)) | K9: =IF(J9="","",IF(J9>=設定!$B$19,"◎ 有力",IF(J9>=設定!$B$20,"○ 候補",IF(J9>=3,"△ 要検討","× 見送り")))) | L9: =IF(E9="","",IF(E9>=設定!$B$14,"○","×")) | M9: =IF(H9="","",IF(H9<=設定!$B$15,"○","×")) | N9: =IF(I9="","",IF(I9>=設定!$B$16,"○","×")) | O9: =IF(G9="","",IF(AND(G9>=設定!$B$17,G9<=設定!$B$18),"○","×")) | P9: =IF(OR(B9="",D9=0),"",COUNTIFS(上位10件データ!$A:$A,$B9,上位10件データ!$H:$H,"はい")/D9)
A10: =IF(B10="","",ROW()-1) | D10: =IF(B10="","",COUNTIFS(上位10件データ!$A:$A,$B10)) | E10: =IF(OR(B10="",D10=0),"",AVERAGEIFS(上位10件データ!$G:$G,上位10件データ!$A:$A,$B10)) | F10: =IF(OR(B10="",D10=0),"",SUMIFS(上位10件データ!$G:$G,上位10件データ!$A:$A,$B10)) | G10: =IF(OR(B10="",D10=0),"",AVERAGEIFS(上位10件データ!$E:$E,上位10件データ!$A:$A,$B10)) | H10: =IF(OR(B10="",D10=0),"",COUNTIFS(上位10件データ!$A:$A,$B10,上位10件データ!$F:$F,">=1000")) | I10: =IF(OR(B10="",D10=0),"",COUNTIFS(上位10件データ!$A:$A,$B10,上位10件データ!$F:$F,"<100")) | J10: =IF(E10="","",COUNTIF(L10:O10,"○")+IF(P10>=0.5,1,0)) | K10: =IF(J10="","",IF(J10>=設定!$B$19,"◎ 有力",IF(J10>=設定!$B$20,"○ 候補",IF(J10>=3,"△ 要検討","× 見送り")))) | L10: =IF(E10="","",IF(E10>=設定!$B$14,"○","×")) | M10: =IF(H10="","",IF(H10<=設定!$B$15,"○","×")) | N10: =IF(I10="","",IF(I10>=設定!$B$16,"○","×")) | O10: =IF(G10="","",IF(AND(G10>=設定!$B$17,G10<=設定!$B$18),"○","×")) | P10: =IF(OR(B10="",D10=0),"",COUNTIFS(上位10件データ!$A:$A,$B10,上位10件データ!$H:$H,"はい")/D10)
A11: =IF(B11="","",ROW()-1) | D11: =IF(B11="","",COUNTIFS(上位10件データ!$A:$A,$B11)) | E11: =IF(OR(B11="",D11=0),"",AVERAGEIFS(上位10件データ!$G:$G,上位10件データ!$A:$A,$B11)) | F11: =IF(OR(B11="",D11=0),"",SUMIFS(上位10件データ!$G:$G,上位10件データ!$A:$A,$B11)) | G11: =IF(OR(B11="",D11=0),"",AVERAGEIFS(上位10件データ!$E:$E,上位10件データ!$A:$A,$B11)) | H11: =IF(OR(B11="",D11=0),"",COUNTIFS(上位10件データ!$A:$A,$B11,上位10件データ!$F:$F,">=1000")) | I11: =IF(OR(B11="",D11=0),"",COUNTIFS(上位10件データ!$A:$A,$B11,上位10件データ!$F:$F,"<100")) | J11: =IF(E11="","",COUNTIF(L11:O11,"○")+IF(P11>=0.5,1,0)) | K11: =IF(J11="","",IF(J11>=設定!$B$19,"◎ 有力",IF(J11>=設定!$B$20,"○ 候補",IF(J11>=3,"△ 要検討","× 見送り")))) | L11: =IF(E11="","",IF(E11>=設定!$B$14,"○","×")) | M11: =IF(H11="","",IF(H11<=設定!$B$15,"○","×")) | N11: =IF(I11="","",IF(I11>=設定!$B$16,"○","×")) | O11: =IF(G11="","",IF(AND(G11>=設定!$B$17,G11<=設定!$B$18),"○","×")) | P11: =IF(OR(B11="",D11=0),"",COUNTIFS(上位10件データ!$A:$A,$B11,上位10件データ!$H:$H,"はい")/D11)
A12: =IF(B12="","",ROW()-1) | D12: =IF(B12="","",COUNTIFS(上位10件データ!$A:$A,$B12)) | E12: =IF(OR(B12="",D12=0),"",AVERAGEIFS(上位10件データ!$G:$G,上位10件データ!$A:$A,$B12)) | F12: =IF(OR(B12="",D12=0),"",SUMIFS(上位10件データ!$G:$G,上位10件データ!$A:$A,$B12)) | G12: =IF(OR(B12="",D12=0),"",AVERAGEIFS(上位10件データ!$E:$E,上位10件データ!$A:$A,$B12)) | H12: =IF(OR(B12="",D12=0),"",COUNTIFS(上位10件データ!$A:$A,$B12,上位10件データ!$F:$F,">=1000")) | I12: =IF(OR(B12="",D12=0),"",COUNTIFS(上位10件データ!$A:$A,$B12,上位10件データ!$F:$F,"<100")) | J12: =IF(E12="","",COUNTIF(L12:O12,"○")+IF(P12>=0.5,1,0)) | K12: =IF(J12="","",IF(J12>=設定!$B$19,"◎ 有力",IF(J12>=設定!$B$20,"○ 候補",IF(J12>=3,"△ 要検討","× 見送り")))) | L12: =IF(E12="","",IF(E12>=設定!$B$14,"○","×")) | M12: =IF(H12="","",IF(H12<=設定!$B$15,"○","×")) | N12: =IF(I12="","",IF(I12>=設定!$B$16,"○","×")) | O12: =IF(G12="","",IF(AND(G12>=設定!$B$17,G12<=設定!$B$18),"○","×")) | P12: =IF(OR(B12="",D12=0),"",COUNTIFS(上位10件データ!$A:$A,$B12,上位10件データ!$H:$H,"はい")/D12)
A13: =IF(B13="","",ROW()-1) | D13: =IF(B13="","",COUNTIFS(上位10件データ!$A:$A,$B13)) | E13: =IF(OR(B13="",D13=0),"",AVERAGEIFS(上位10件データ!$G:$G,上位10件データ!$A:$A,$B13)) | F13: =IF(OR(B13="",D13=0),"",SUMIFS(上位10件データ!$G:$G,上位10件データ!$A:$A,$B13)) | G13: =IF(OR(B13="",D13=0),"",AVERAGEIFS(上位10件データ!$E:$E,上位10件データ!$A:$A,$B13)) | H13: =IF(OR(B13="",D13=0),"",COUNTIFS(上位10件データ!$A:$A,$B13,上位10件データ!$F:$F,">=1000")) | I13: =IF(OR(B13="",D13=0),"",COUNTIFS(上位10件データ!$A:$A,$B13,上位10件データ!$F:$F,"<100")) | J13: =IF(E13="","",COUNTIF(L13:O13,"○")+IF(P13>=0.5,1,0)) | K13: =IF(J13="","",IF(J13>=設定!$B$19,"◎ 有力",IF(J13>=設定!$B$20,"○ 候補",IF(J13>=3,"△ 要検討","× 見送り")))) | L13: =IF(E13="","",IF(E13>=設定!$B$14,"○","×")) | M13: =IF(H13="","",IF(H13<=設定!$B$15,"○","×")) | N13: =IF(I13="","",IF(I13>=設定!$B$16,"○","×")) | O13: =IF(G13="","",IF(AND(G13>=設定!$B$17,G13<=設定!$B$18),"○","×")) | P13: =IF(OR(B13="",D13=0),"",COUNTIFS(上位10件データ!$A:$A,$B13,上位10件データ!$H:$H,"はい")/D13)
A14: =IF(B14="","",ROW()-1) | D14: =IF(B14="","",COUNTIFS(上位10件データ!$A:$A,$B14)) | E14: =IF(OR(B14="",D14=0),"",AVERAGEIFS(上位10件データ!$G:$G,上位10件データ!$A:$A,$B14)) | F14: =IF(OR(B14="",D14=0),"",SUMIFS(上位10件データ!$G:$G,上位10件データ!$A:$A,$B14)) | G14: =IF(OR(B14="",D14=0),"",AVERAGEIFS(上位10件データ!$E:$E,上位10件データ!$A:$A,$B14)) | H14: =IF(OR(B14="",D14=0),"",COUNTIFS(上位10件データ!$A:$A,$B14,上位10件データ!$F:$F,">=1000")) | I14: =IF(OR(B14="",D14=0),"",COUNTIFS(上位10件データ!$A:$A,$B14,上位10件データ!$F:$F,"<100")) | J14: =IF(E14="","",COUNTIF(L14:O14,"○")+IF(P14>=0.5,1,0)) | K14: =IF(J14="","",IF(J14>=設定!$B$19,"◎ 有力",IF(J14>=設定!$B$20,"○ 候補",IF(J14>=3,"△ 要検討","× 見送り")))) | L14: =IF(E14="","",IF(E14>=設定!$B$14,"○","×")) | M14: =IF(H14="","",IF(H14<=設定!$B$15,"○","×")) | N14: =IF(I14="","",IF(I14>=設定!$B$16,"○","×")) | O14: =IF(G14="","",IF(AND(G14>=設定!$B$17,G14<=設定!$B$18),"○","×")) | P14: =IF(OR(B14="",D14=0),"",COUNTIFS(上位10件データ!$A:$A,$B14,上位10件データ!$H:$H,"はい")/D14)
... A201: =IF(B201="","",ROW()-1) | D201: =IF(B201="","",COUNTIFS(上位10件データ!$A:$A,$B201)) | E201: =IF(OR(B201="",D201=0),"",AVERAGEIFS(上位10件データ!$G:$G,上位10件データ!$A:$A,$B201)) | F201: =IF(OR(B201="",D201=0),"",SUMIFS(上位10件データ!$G:$G,上位10件データ!$A:$A,$B201)) | G201: =IF(OR(B201="",D201=0),"",AVERAGEIFS(上位10件データ!$E:$E,上位10件データ!$A:$A,$B201)) | H201: =IF(OR(B201="",D201=0),"",COUNTIFS(上位10件データ!$A:$A,$B201,上位10件データ!$F:$F,">=1000")) | I201: =IF(OR(B201="",D201=0),"",COUNTIFS(上位10件データ!$A:$A,$B201,上位10件データ!$F:$F,"<100")) | J201: =IF(E201="","",COUNTIF(L201:O201,"○")+IF(P201>=0.5,1,0)) | K201: =IF(J201="","",IF(J201>=設定!$B$19,"◎ 有力",IF(J201>=設定!$B$20,"○ 候補",IF(J201>=3,"△ 要検討","× 見送り")))) | L201: =IF(E201="","",IF(E201>=設定!$B$14,"○","×")) | M201: =IF(H201="","",IF(H201<=設定!$B$15,"○","×")) | N201: =IF(I201="","",IF(I201>=設定!$B$16,"○","×")) | O201: =IF(G201="","",IF(AND(G201>=設定!$B$17,G201<=設定!$B$18),"○","×")) | P201: =IF(OR(B201="",D201=0),"",COUNTIFS(上位10件データ!$A:$A,$B201,上位10件データ!$H:$H,"はい")/D201)

Sheet 利益計算
A1: 商品名 | B1: 販売価格（円） | C1: 仕入れ単価（元） | D1: 中国国内送料（元/個） | E1: 国際送料（円/個） | F1: OEM費用（円/個） | G1: 仕入れ原価（円/個） | H1: 関税・消費税（円/個） | I1: Amazon手数料（円/個） | J1: 1個あたり利益（円） | K1: 利益率 | L1: ROI | M1: 目標達成に必要な月販（個） | N1: 予算で仕入れられる数（個） | O1: 最低ロット（個） | P1: 判定
A2: （例）裏起毛ネックウォーマー | B2: 1580 | C2: 12 | D2: 1 | E2: 120 | F2: 60 | G2: =IF(B2="","",(C2+D2)*設定!$B$6*(1+設定!$B$7)+E2+F2) -> 466.65 | H2: =IF(B2="","",ROUND(G2*設定!$B$8+G2*(1+設定!$B$8)*設定!$B$9,0)) -> 98 | I2: =IF(B2="","",ROUND(B2*設定!$B$10,0)+設定!$B$11+設定!$B$12) -> 496 | J2: =IF(B2="","",B2-G2-H2-I2) -> 519.35 | K2: =IF(B2="","",IFERROR(J2/B2,"")) -> 0.32870253 | L2: =IF(B2="","",IFERROR(J2/(G2+H2),"")) -> 0.91977331 | M2: =IF(B2="","",IF(J2<=0,"赤字",ROUNDUP(設定!$B$3/J2,0))) -> 97 | N2: =IF(B2="","",IFERROR(ROUNDDOWN(設定!$B$4/(G2+H2),0),"")) -> 88 | O2: 50 | P2: =IF(B2="","",IF(J2<=0,"× 赤字",IF(AND(K2>=設定!$B$22,J2>=設定!$B$23),IF(AND(O2<>"",N2<O2),"△ 予算不足","○ OK"),"△ 利益薄い"))) -> ○ OK
G3: =IF(B3="","",(C3+D3)*設定!$B$6*(1+設定!$B$7)+E3+F3) | H3: =IF(B3="","",ROUND(G3*設定!$B$8+G3*(1+設定!$B$8)*設定!$B$9,0)) | I3: =IF(B3="","",ROUND(B3*設定!$B$10,0)+設定!$B$11+設定!$B$12) | J3: =IF(B3="","",B3-G3-H3-I3) | K3: =IF(B3="","",IFERROR(J3/B3,"")) | L3: =IF(B3="","",IFERROR(J3/(G3+H3),"")) | M3: =IF(B3="","",IF(J3<=0,"赤字",ROUNDUP(設定!$B$3/J3,0))) | N3: =IF(B3="","",IFERROR(ROUNDDOWN(設定!$B$4/(G3+H3),0),"")) | P3: =IF(B3="","",IF(J3<=0,"× 赤字",IF(AND(K3>=設定!$B$22,J3>=設定!$B$23),IF(AND(O3<>"",N3<O3),"△ 予算不足","○ OK"),"△ 利益薄い")))
G4: =IF(B4="","",(C4+D4)*設定!$B$6*(1+設定!$B$7)+E4+F4) | H4: =IF(B4="","",ROUND(G4*設定!$B$8+G4*(1+設定!$B$8)*設定!$B$9,0)) | I4: =IF(B4="","",ROUND(B4*設定!$B$10,0)+設定!$B$11+設定!$B$12) | J4: =IF(B4="","",B4-G4-H4-I4) | K4: =IF(B4="","",IFERROR(J4/B4,"")) | L4: =IF(B4="","",IFERROR(J4/(G4+H4),"")) | M4: =IF(B4="","",IF(J4<=0,"赤字",ROUNDUP(設定!$B$3/J4,0))) | N4: =IF(B4="","",IFERROR(ROUNDDOWN(設定!$B$4/(G4+H4),0),"")) | P4: =IF(B4="","",IF(J4<=0,"× 赤字",IF(AND(K4>=設定!$B$22,J4>=設定!$B$23),IF(AND(O4<>"",N4<O4),"△ 予算不足","○ OK"),"△ 利益薄い")))
G5: =IF(B5="","",(C5+D5)*設定!$B$6*(1+設定!$B$7)+E5+F5) | H5: =IF(B5="","",ROUND(G5*設定!$B$8+G5*(1+設定!$B$8)*設定!$B$9,0)) | I5: =IF(B5="","",ROUND(B5*設定!$B$10,0)+設定!$B$11+設定!$B$12) | J5: =IF(B5="","",B5-G5-H5-I5) | K5: =IF(B5="","",IFERROR(J5/B5,"")) | L5: =IF(B5="","",IFERROR(J5/(G5+H5),"")) | M5: =IF(B5="","",IF(J5<=0,"赤字",ROUNDUP(設定!$B$3/J5,0))) | N5: =IF(B5="","",IFERROR(ROUNDDOWN(設定!$B$4/(G5+H5),0),"")) | P5: =IF(B5="","",IF(J5<=0,"× 赤字",IF(AND(K5>=設定!$B$22,J5>=設定!$B$23),IF(AND(O5<>"",N5<O5),"△ 予算不足","○ OK"),"△ 利益薄い")))
G6: =IF(B6="","",(C6+D6)*設定!$B$6*(1+設定!$B$7)+E6+F6) | H6: =IF(B6="","",ROUND(G6*設定!$B$8+G6*(1+設定!$B$8)*設定!$B$9,0)) | I6: =IF(B6="","",ROUND(B6*設定!$B$10,0)+設定!$B$11+設定!$B$12) | J6: =IF(B6="","",B6-G6-H6-I6) | K6: =IF(B6="","",IFERROR(J6/B6,"")) | L6: =IF(B6="","",IFERROR(J6/(G6+H6),"")) | M6: =IF(B6="","",IF(J6<=0,"赤字",ROUNDUP(設定!$B$3/J6,0))) | N6: =IF(B6="","",IFERROR(ROUNDDOWN(設定!$B$4/(G6+H6),0),"")) | P6: =IF(B6="","",IF(J6<=0,"× 赤字",IF(AND(K6>=設定!$B$22,J6>=設定!$B$23),IF(AND(O6<>"",N6<O6),"△ 予算不足","○ OK"),"△ 利益薄い")))
G7: =IF(B7="","",(C7+D7)*設定!$B$6*(1+設定!$B$7)+E7+F7) | H7: =IF(B7="","",ROUND(G7*設定!$B$8+G7*(1+設定!$B$8)*設定!$B$9,0)) | I7: =IF(B7="","",ROUND(B7*設定!$B$10,0)+設定!$B$11+設定!$B$12) | J7: =IF(B7="","",B7-G7-H7-I7) | K7: =IF(B7="","",IFERROR(J7/B7,"")) | L7: =IF(B7="","",IFERROR(J7/(G7+H7),"")) | M7: =IF(B7="","",IF(J7<=0,"赤字",ROUNDUP(設定!$B$3/J7,0))) | N7: =IF(B7="","",IFERROR(ROUNDDOWN(設定!$B$4/(G7+H7),0),"")) | P7: =IF(B7="","",IF(J7<=0,"× 赤字",IF(AND(K7>=設定!$B$22,J7>=設定!$B$23),IF(AND(O7<>"",N7<O7),"△ 予算不足","○ OK"),"△ 利益薄い")))
G8: =IF(B8="","",(C8+D8)*設定!$B$6*(1+設定!$B$7)+E8+F8) | H8: =IF(B8="","",ROUND(G8*設定!$B$8+G8*(1+設定!$B$8)*設定!$B$9,0)) | I8: =IF(B8="","",ROUND(B8*設定!$B$10,0)+設定!$B$11+設定!$B$12) | J8: =IF(B8="","",B8-G8-H8-I8) | K8: =IF(B8="","",IFERROR(J8/B8,"")) | L8: =IF(B8="","",IFERROR(J8/(G8+H8),"")) | M8: =IF(B8="","",IF(J8<=0,"赤字",ROUNDUP(設定!$B$3/J8,0))) | N8: =IF(B8="","",IFERROR(ROUNDDOWN(設定!$B$4/(G8+H8),0),"")) | P8: =IF(B8="","",IF(J8<=0,"× 赤字",IF(AND(K8>=設定!$B$22,J8>=設定!$B$23),IF(AND(O8<>"",N8<O8),"△ 予算不足","○ OK"),"△ 利益薄い")))
G9: =IF(B9="","",(C9+D9)*設定!$B$6*(1+設定!$B$7)+E9+F9) | H9: =IF(B9="","",ROUND(G9*設定!$B$8+G9*(1+設定!$B$8)*設定!$B$9,0)) | I9: =IF(B9="","",ROUND(B9*設定!$B$10,0)+設定!$B$11+設定!$B$12) | J9: =IF(B9="","",B9-G9-H9-I9) | K9: =IF(B9="","",IFERROR(J9/B9,"")) | L9: =IF(B9="","",IFERROR(J9/(G9+H9),"")) | M9: =IF(B9="","",IF(J9<=0,"赤字",ROUNDUP(設定!$B$3/J9,0))) | N9: =IF(B9="","",IFERROR(ROUNDDOWN(設定!$B$4/(G9+H9),0),"")) | P9: =IF(B9="","",IF(J9<=0,"× 赤字",IF(AND(K9>=設定!$B$22,J9>=設定!$B$23),IF(AND(O9<>"",N9<O9),"△ 予算不足","○ OK"),"△ 利益薄い")))
G10: =IF(B10="","",(C10+D10)*設定!$B$6*(1+設定!$B$7)+E10+F10) | H10: =IF(B10="","",ROUND(G10*設定!$B$8+G10*(1+設定!$B$8)*設定!$B$9,0)) | I10: =IF(B10="","",ROUND(B10*設定!$B$10,0)+設定!$B$11+設定!$B$12) | J10: =IF(B10="","",B10-G10-H10-I10) | K10: =IF(B10="","",IFERROR(J10/B10,"")) | L10: =IF(B10="","",IFERROR(J10/(G10+H10),"")) | M10: =IF(B10="","",IF(J10<=0,"赤字",ROUNDUP(設定!$B$3/J10,0))) | N10: =IF(B10="","",IFERROR(ROUNDDOWN(設定!$B$4/(G10+H10),0),"")) | P10: =IF(B10="","",IF(J10<=0,"× 赤字",IF(AND(K10>=設定!$B$22,J10>=設定!$B$23),IF(AND(O10<>"",N10<O10),"△ 予算不足","○ OK"),"△ 利益薄い")))
G11: =IF(B11="","",(C11+D11)*設定!$B$6*(1+設定!$B$7)+E11+F11) | H11: =IF(B11="","",ROUND(G11*設定!$B$8+G11*(1+設定!$B$8)*設定!$B$9,0)) | I11: =IF(B11="","",ROUND(B11*設定!$B$10,0)+設定!$B$11+設定!$B$12) | J11: =IF(B11="","",B11-G11-H11-I11) | K11: =IF(B11="","",IFERROR(J11/B11,"")) | L11: =IF(B11="","",IFERROR(J11/(G11+H11),"")) | M11: =IF(B11="","",IF(J11<=0,"赤字",ROUNDUP(設定!$B$3/J11,0))) | N11: =IF(B11="","",IFERROR(ROUNDDOWN(設定!$B$4/(G11+H11),0),"")) | P11: =IF(B11="","",IF(J11<=0,"× 赤字",IF(AND(K11>=設定!$B$22,J11>=設定!$B$23),IF(AND(O11<>"",N11<O11),"△ 予算不足","○ OK"),"△ 利益薄い")))
G12: =IF(B12="","",(C12+D12)*設定!$B$6*(1+設定!$B$7)+E12+F12) | H12: =IF(B12="","",ROUND(G12*設定!$B$8+G12*(1+設定!$B$8)*設定!$B$9,0)) | I12: =IF(B12="","",ROUND(B12*設定!$B$10,0)+設定!$B$11+設定!$B$12) | J12: =IF(B12="","",B12-G12-H12-I12) | K12: =IF(B12="","",IFERROR(J12/B12,"")) | L12: =IF(B12="","",IFERROR(J12/(G12+H12),"")) | M12: =IF(B12="","",IF(J12<=0,"赤字",ROUNDUP(設定!$B$3/J12,0))) | N12: =IF(B12="","",IFERROR(ROUNDDOWN(設定!$B$4/(G12+H12),0),"")) | P12: =IF(B12="","",IF(J12<=0,"× 赤字",IF(AND(K12>=設定!$B$22,J12>=設定!$B$23),IF(AND(O12<>"",N12<O12),"△ 予算不足","○ OK"),"△ 利益薄い")))
G13: =IF(B13="","",(C13+D13)*設定!$B$6*(1+設定!$B$7)+E13+F13) | H13: =IF(B13="","",ROUND(G13*設定!$B$8+G13*(1+設定!$B$8)*設定!$B$9,0)) | I13: =IF(B13="","",ROUND(B13*設定!$B$10,0)+設定!$B$11+設定!$B$12) | J13: =IF(B13="","",B13-G13-H13-I13) | K13: =IF(B13="","",IFERROR(J13/B13,"")) | L13: =IF(B13="","",IFERROR(J13/(G13+H13),"")) | M13: =IF(B13="","",IF(J13<=0,"赤字",ROUNDUP(設定!$B$3/J13,0))) | N13: =IF(B13="","",IFERROR(ROUNDDOWN(設定!$B$4/(G13+H13),0),"")) | P13: =IF(B13="","",IF(J13<=0,"× 赤字",IF(AND(K13>=設定!$B$22,J13>=設定!$B$23),IF(AND(O13<>"",N13<O13),"△ 予算不足","○ OK"),"△ 利益薄い")))
G14: =IF(B14="","",(C14+D14)*設定!$B$6*(1+設定!$B$7)+E14+F14) | H14: =IF(B14="","",ROUND(G14*設定!$B$8+G14*(1+設定!$B$8)*設定!$B$9,0)) | I14: =IF(B14="","",ROUND(B14*設定!$B$10,0)+設定!$B$11+設定!$B$12) | J14: =IF(B14="","",B14-G14-H14-I14) | K14: =IF(B14="","",IFERROR(J14/B14,"")) | L14: =IF(B14="","",IFERROR(J14/(G14+H14),"")) | M14: =IF(B14="","",IF(J14<=0,"赤字",ROUNDUP(設定!$B$3/J14,0))) | N14: =IF(B14="","",IFERROR(ROUNDDOWN(設定!$B$4/(G14+H14),0),"")) | P14: =IF(B14="","",IF(J14<=0,"× 赤字",IF(AND(K14>=設定!$B$22,J14>=設定!$B$23),IF(AND(O14<>"",N14<O14),"△ 予算不足","○ OK"),"△ 利益薄い")))
... G201: =IF(B201="","",(C201+D201)*設定!$B$6*(1+設定!$B$7)+E201+F201) | H201: =IF(B201="","",ROUND(G201*設定!$B$8+G201*(1+設定!$B$8)*設定!$B$9,0)) | I201: =IF(B201="","",ROUND(B201*設定!$B$10,0)+設定!$B$11+設定!$B$12) | J201: =IF(B201="","",B201-G201-H201-I201) | K201: =IF(B201="","",IFERROR(J201/B201,"")) | L201: =IF(B201="","",IFERROR(J201/(G201+H201),"")) | M201: =IF(B201="","",IF(J201<=0,"赤字",ROUNDUP(設定!$B$3/J201,0))) | N201: =IF(B201="","",IFERROR(ROUNDDOWN(設定!$B$4/(G201+H201),0),"")) | P201: =IF(B201="","",IF(J201<=0,"× 赤字",IF(AND(K201>=設定!$B$22,J201>=設定!$B$23),IF(AND(O201<>"",N201<O201),"△ 予算不足","○ OK"),"△ 利益薄い")))
